[{"id":1,"nome":"Jamal","email":"niger.com","senha":"1234","endereço":"Jacob Hartheman","telefone":"14997470330","cpf":"46967020811"},{"id":2,"nome":"Adenilson","email":"MOElester@gmail.com","senha":"criancinha123","endereço":"Rua Criança Esperança","telefone":1491725791,"cpf":12166361928},{"id":3,"nome":"John Doe","email":"who@gmail.com","senha":"$2b$10$EyJGEk9uyIKAhmvHKqjD0O89yidI3E8DQdcpr1tNv67QLrNwOFJPq","endereço":"Rua Vazia","telefone":14991293045,"cpf":97563749801},{"id":4,"nome":"Bartholomeu","email":"seila@gmail.com","senha":"$2b$10$WFQUYjrJhOpup/0539.2xO/D6CHWS39BpttS6jb0fOFht9kbpz7MG","endereço":"jacob hartheman","telefone":"14997470330","cpf":"46967020821"},{"id":5,"nome":"Bartholomeu","email":"seila@gmail.com","senha":"$2b$10$70P4.k8.EKF2WVbfdSNa5OufzttEFNCE3rLTlbUMTTpZuMFtvG1e2","endereço":"jacob hartheman","telefone":"14997470330","cpf":"46967920821"}]